orcpy/__init__.py
orcpy/design/__init__.py
orcpy-0.1.2.dist-info/METADATA
orcpy-0.1.2.dist-info/WHEEL
orcpy-0.1.2.dist-info/RECORD
