Metadata-Version: 2.1
Name: orcpy
Version: 0.1.2
Summary: A python package for designing organic Rankine cycles
Author: Mehran Ahmadpour
Author-email: mehran.hmdpr@gmail.com
Requires-Python: >=3.8,<4.0
Classifier: Programming Language :: Python :: 3
Classifier: Programming Language :: Python :: 3.8
Classifier: Programming Language :: Python :: 3.9
Classifier: Programming Language :: Python :: 3.10
Classifier: Programming Language :: Python :: 3.11
Requires-Dist: coolprop (>=6.4.3.post1,<7.0.0)
Requires-Dist: pandas (>=1.5.3,<2.0.0)
Requires-Dist: pina (>=0.1.1,<0.2.0)
Requires-Dist: plotly (>=5.13.0,<6.0.0)
Requires-Dist: requests (>=2.28.2,<3.0.0)
